{
  "artifact": "phase-64-github-sync-smoke-20260716",
  "date": "2026-07-16",
  "workspace": "selected local workspace",
  "status": "verified",
  "checks": {
    "clone": {
      "status": "verified",
      "summary": "Repository clone path verified for the GitHub sync smoke flow."
    },
    "commit": {
      "status": "verified",
      "summary": "Local commit path verified for the GitHub sync smoke flow."
    },
    "push": {
      "status": "verified",
      "summary": "Remote push path verified for the GitHub sync smoke flow."
    }
  },
  "deliverables": [
    "README.md",
    "status.json"
  ]
}
